src/__init__.py
src/cli.py
src/generator.py
src/models.py
src/plugin.py
src/utils.py
src/Litestar/__init__.py
src/Litestar/generator.py
src/Litestar/App/__init__.py.jinja
src/Litestar/App/__main__.py.jinja
src/Litestar/App/app.py.jinja
src/Litestar/App/config.py.jinja
src/Litestar/App/settings.py.jinja
src/Litestar/App/controllers/__init__.py.jinja
src/Litestar/App/controllers/users.py.jinja
src/Litestar/App/lib/__init__.py.jinja
src/Litestar/App/lib/utils.py.jinja
src/Litestar/App/schemas/__init__.py.jinja
src/Litestar/App/schemas/users.py.jinja
src/Litestar/Config/.env.example.jinja
src/Litestar/Config/.gitignore.jinja
src/Litestar/Config/.pre-commit-config.yaml.jinja
src/Litestar/Config/.python-version.jinja
src/Litestar/Config/Makefile.jinja
src/Litestar/Config/README.md.jinja
src/Litestar/Config/pyproject.toml.jinja
src/Litestar/Containers/Dockerfile.jinja
src/Litestar/Containers/docker-compose.infra.yml.jinja
src/Litestar/Containers/docker-compose.yml.jinja
src/Litestar/Plugins/__init__.py
src/Litestar/Plugins/AdvancedAlchemy/__init__.py
src/Litestar/Plugins/AdvancedAlchemy/Templates/lib/dependencies.py.jinja
src/Litestar/Plugins/AdvancedAlchemy/Templates/lib/services.py.jinja
src/Litestar/Plugins/AdvancedAlchemy/Templates/models/__init__.py.jinja
src/Litestar/Plugins/AdvancedAlchemy/Templates/models/users.py.jinja
src/Litestar/Plugins/LitestarSAQ/.gitkeep
src/Litestar/Plugins/LitestarSAQ/__init__.py
src/Litestar/Plugins/LitestarVite/.gitkeep
src/Litestar/Plugins/LitestarVite/__init__.py
litestar_start-0.1.0a15.dist-info/METADATA
litestar_start-0.1.0a15.dist-info/WHEEL
litestar_start-0.1.0a15.dist-info/entry_points.txt
litestar_start-0.1.0a15.dist-info/licenses/LICENSE
litestar_start-0.1.0a15.dist-info/RECORD
